seeker/__init__.py
seeker/admin.py
seeker/apps.py
seeker/dsl.py
seeker/facets.py
seeker/forms.py
seeker/indexer.py
seeker/mapping.py
seeker/middleware.py
seeker/models.py
seeker/registry.py
seeker/signals.py
seeker/utils.py
seeker/views.py
seeker/management/__init__.py
seeker/management/commands/__init__.py
seeker/management/commands/dropindex.py
seeker/management/commands/dumpindex.py
seeker/management/commands/loadindex.py
seeker/management/commands/reindex.py
seeker/migrations/0001_initial.py
seeker/migrations/0002_auto_20150507_0134.py
seeker/migrations/0003_auto_20180214_1501.py
seeker/migrations/0004_auto_20180322_1412.py
seeker/migrations/0005_auto_20180330_1708.py
seeker/migrations/0006_auto_20190625_1139.py
seeker/migrations/__init__.py
seeker/templates/advanced_seeker/footer.html
seeker/templates/advanced_seeker/header.html
seeker/templates/advanced_seeker/pager.html
seeker/templates/advanced_seeker/results.html
seeker/templates/advanced_seeker/save_form.html
seeker/templates/advanced_seeker/seeker.html
seeker/templates/advanced_seeker/facets/date_range.html
seeker/templates/advanced_seeker/facets/range.html
seeker/templates/advanced_seeker/facets/terms.html
seeker/templates/advanced_seeker/facets/text.html
seeker/templates/advanced_seeker/facets/year_histogram.html
seeker/templates/seeker/column.html
seeker/templates/seeker/footer.html
seeker/templates/seeker/form.html
seeker/templates/seeker/header.html
seeker/templates/seeker/pager.html
seeker/templates/seeker/results.html
seeker/templates/seeker/save.html
seeker/templates/seeker/score.html
seeker/templates/seeker/seeker.html
seeker/templates/seeker/facets/range.html
seeker/templates/seeker/facets/terms.html
seeker/templates/seeker/facets/text.html
seeker/templates/seeker/facets/year_histogram.html
seeker/templatetags/__init__.py
seeker/templatetags/seeker.py
django_seeker-8.0.0.dist-info/METADATA
django_seeker-8.0.0.dist-info/WHEEL
django_seeker-8.0.0.dist-info/licenses/LICENSE
django_seeker-8.0.0.dist-info/RECORD
